django_mptt2-0.2.1.dist-info/licenses/LICENSE
mptt2/__init__.py
mptt2/admin.py
mptt2/apps.py
mptt2/compatibility.py
mptt2/enums.py
mptt2/exceptions.py
mptt2/expressions.py
mptt2/managers.py
mptt2/models.py
mptt2/query.py
mptt2/locale/de/LC_MESSAGES/django.po
mptt2/migrations/0001_initial.py
mptt2/migrations/__init__.py
mptt2/templates/admin/mptt_change_list.html
mptt2/templates/admin/mptt_change_list_results.html
mptt2/templates/admin/mptt_draggable_change_list.html
mptt2/templatetags/__init__.py
mptt2/templatetags/mptt_admin.py
django_mptt2-0.2.1.dist-info/METADATA
django_mptt2-0.2.1.dist-info/WHEEL
django_mptt2-0.2.1.dist-info/top_level.txt
django_mptt2-0.2.1.dist-info/RECORD
