Metadata-Version: 2.4
Name: django-mptt2
Version: 0.2.1
Summary: Utilities for implementing Modified Preorder Tree Traversal with your Django Models and working with trees of Model instances.
Home-page: https://github.com/jokiefer/django-mptt2/
Author: Jonas Kiefer
Author-email: jonas.kiefer@live.com
License: MIT-License
Platform: OS Independent
Classifier: Development Status :: 3 - Alpha
Classifier: Intended Audience :: Developers
Classifier: Natural Language :: English
Classifier: Topic :: Internet :: WWW/HTTP
Classifier: Environment :: Web Environment
Classifier: Framework :: Django
Classifier: Topic :: Software Development :: Libraries
Classifier: License :: OSI Approved :: MIT License
Classifier: Operating System :: OS Independent
Classifier: Framework :: Django
Classifier: Framework :: Django :: 4.2
Classifier: Programming Language :: Python
Classifier: Programming Language :: Python :: 3.8
Classifier: Programming Language :: Python :: 3.9
Classifier: Programming Language :: Python :: 3.10
Requires-Python: >=3.8
License-File: LICENSE
Provides-Extra: tests
Requires-Dist: coverage; extra == "tests"
Dynamic: license-file
